mop_utils/__init__.py
mop_utils/base_model_wrapper.py
mop_utils/constant.py
mop_utils/inference_wrapper.py
mop_utils/util.py
mop_utils-2.6.dist-info/METADATA
mop_utils-2.6.dist-info/WHEEL
mop_utils-2.6.dist-info/top_level.txt
mop_utils-2.6.dist-info/RECORD
